jaxtyping/__init__.py
jaxtyping/_array_types.py
jaxtyping/_config.py
jaxtyping/_decorator.py
jaxtyping/_errors.py
jaxtyping/_import_hook.py
jaxtyping/_indirection.py
jaxtyping/_ipython_extension.py
jaxtyping/_pytest_plugin.py
jaxtyping/_pytree_type.py
jaxtyping/_storage.py
jaxtyping/py.typed
jaxtyping/_typeguard/LICENSE
jaxtyping/_typeguard/README.md
jaxtyping/_typeguard/__init__.py
jaxtyping-0.3.7.dist-info/METADATA
jaxtyping-0.3.7.dist-info/WHEEL
jaxtyping-0.3.7.dist-info/entry_points.txt
jaxtyping-0.3.7.dist-info/licenses/LICENSE
jaxtyping-0.3.7.dist-info/RECORD
